README.md
pyproject.toml
setup.cfg
setup.py
fastapi_databases/__init__.py
fastapi_databases.egg-info/PKG-INFO
fastapi_databases.egg-info/SOURCES.txt
fastapi_databases.egg-info/dependency_links.txt
fastapi_databases.egg-info/entry_points.txt
fastapi_databases.egg-info/not-zip-safe
fastapi_databases.egg-info/requires.txt
fastapi_databases.egg-info/top_level.txt